README.md
setup.cfg
setup.py
sparsembed/__init__.py
sparsembed/__version__.py
sparsembed.egg-info/PKG-INFO
sparsembed.egg-info/SOURCES.txt
sparsembed.egg-info/dependency_links.txt
sparsembed.egg-info/requires.txt
sparsembed.egg-info/top_level.txt
sparsembed/losses/__init__.py
sparsembed/losses/flops.py
sparsembed/losses/ranking.py
sparsembed/model/__init__.py
sparsembed/model/sparsembed.py
sparsembed/model/splade.py
sparsembed/retrieve/__init__.py
sparsembed/retrieve/sparsembed_retriever.py
sparsembed/retrieve/splade_retriever.py
sparsembed/train/__init__.py
sparsembed/train/train_sparsembed.py
sparsembed/train/train_splade.py
sparsembed/utils/__init__.py
sparsembed/utils/dense_scores.py
sparsembed/utils/evaluate.py
sparsembed/utils/in_batch.py
sparsembed/utils/iter.py
sparsembed/utils/sparse_scores.py