Metadata-Version: 2.1
Name: sparsembed
Version: 0.0.4
Summary: Sparse Embeddings for Neural Search.
Home-page: https://github.com/raphaelsty/sparseembed
Download-URL: https://github.com/user/sparseembed/archive/v_01.tar.gz
Author: Raphael Sourty
Author-email: raphael.sourty@gmail.com
Keywords: neural search,information retrieval,semantic search,SparseEmbed,Google Research,SPLADE
Classifier: Programming Language :: Python :: 3
Classifier: License :: OSI Approved :: MIT License
Classifier: Operating System :: OS Independent
Requires-Python: >=3.6
Provides-Extra: eval
